py_simple_network/__init__.py
py_simple_network/client.py
py_simple_network/server.py
py_simple_network-1.1.0.dist-info/licenses/LICENCE
py_simple_network-1.1.0.dist-info/METADATA
py_simple_network-1.1.0.dist-info/WHEEL
py_simple_network-1.1.0.dist-info/top_level.txt
py_simple_network-1.1.0.dist-info/RECORD
