Metadata-Version: 2.4
Name: py-simple-network
Version: 1.1.0
Summary: A Python library for simple TCP-based client-server communication
Home-page: https://github.com/GeovaneDev54/py-simple-network
Author: GeovaneDev54
Author-email: geovanethecoder@gmail.com
License: MIT
Classifier: Programming Language :: Python :: 3
Classifier: License :: OSI Approved :: MIT License
Classifier: Operating System :: OS Independent
Requires-Python: >=3.6
License-File: LICENCE
Dynamic: author
Dynamic: author-email
Dynamic: classifier
Dynamic: description
Dynamic: description-content-type
Dynamic: home-page
Dynamic: license
Dynamic: license-file
Dynamic: requires-python
Dynamic: summary
